{
  "name":           "TDR_AIU_MTSMS",
  "path":           "hdfs:///local-filestream/TDR_AIU_MTSMS",
  "sink":           "hdfs:///user/hive/warehouse/tdr.db/tdr_aiu_mtsms",
  "schema":         "tdr",
  "partitions":     700,
  "fileBuffer":     1000,
  "partitionField": "starttime",
  "data":  [
    {"name": "TDRID", "type":   "string"},
    {"name": "SYSID", "type":   "int"},
    {"name": "ORGCDRID", "type":    "string"},
    {"name": "ABISCDRID", "type":   "string"},
    {"name": "ACDRID", "type":  "string"},
    {"name": "REFID", "type":   "string"},
    {"name": "ZONEID", "type":  "bigint"},
    {"name": "POOLID", "type":  "bigint"},
    {"name": "SCCPID", "type":  "string"},
    {"name": "STARTTIME", "type":   "int"},
    {"name": "MILLISEC", "type":    "int"},
    {"name": "ABIS", "type":    "int"},
    {"name": "SRVSTAT", "type": "int"},
    {"name": "CDRSTAT", "type": "int"},
    {"name": "NI", "type":  "int"},
    {"name": "OPC", "type": "int"},
    {"name": "DPC", "type": "int"},
    {"name": "LINKSETID", "type":   "int"},
    {"name": "ACCESS_TYPE", "type": "int"},
    {"name": "IMSI", "type":    "string"},
    {"name": "IMEI", "type":    "string"},
    {"name": "TMSI", "type":    "string"},
    {"name": "MSISDN", "type":  "string"},
    {"name": "OPPint", "type":   "string"},
    {"name": "MCC", "type": "string"},
    {"name": "MNC", "type": "string"},
    {"name": "LAC", "type": "string"},
    {"name": "CI", "type":  "string"},
    {"name": "FIRSTLAC", "type":    "string"},
    {"name": "FIRSTCI", "type": "string"},
    {"name": "MIDCALLSMS", "type":  "int"},
    {"name": "SMCADDR", "type": "string"},
    {"name": "SERVICEKEY", "type":  "bigint"},
    {"name": "SCPNO", "type":   "string"},
    {"name": "CAPVERSION", "type":  "int"},
    {"name": "FIRPAGING_TIME", "type":  "bigint"},
    {"name": "SECPAGING_TIME", "type":  "bigint"},
    {"name": "THIRDPAGING_TIME", "type":    "bigint"},
    {"name": "FOURTHPAGING_TIME", "type":   "bigint"},
    {"name": "FIFTHPAGING_TIME", "type":    "bigint"},
    {"name": "IMM_ASS_COMD_TIME", "type":   "bigint"},
    {"name": "IMM_ASS_REJ_TIME", "type":    "bigint"},
    {"name": "IMM_ASS_COMP_TIME", "type":   "bigint"},
    {"name": "PAGINGRSP_TIME", "type":  "bigint"},
    {"name": "AUTH_REQ_TIME", "type":   "bigint"},
    {"name": "AUTH_RSP_TIME", "type":   "bigint"},
    {"name": "IDENTITY_REQ_TIME", "type":   "bigint"},
    {"name": "IDENTITY_RSP_TIME", "type":   "bigint"},
    {"name": "CIPH_REQ_TIME", "type":   "bigint"},
    {"name": "CIPH_RSP_TIME", "type":   "bigint"},
    {"name": "SMS_RECEIVE_TIME", "type":    "bigint"},
    {"name": "FIRCPDATATIME", "type":   "bigint"},
    {"name": "FIRCPACKTIME", "type":    "bigint"},
    {"name": "SNDCPDATATIME", "type":   "bigint"},
    {"name": "SNDCPACKTIME", "type":    "bigint"},
    {"name": "CLEAR_REQ_TIME", "type":  "bigint"},
    {"name": "END_TIME", "type":    "bigint"},
    {"name": "PPD", "type": "int"},
    {"name": "REL_PHASE", "type":   "int"},
    {"name": "PD", "type":  "int"},
    {"name": "FIRFAILMSG", "type":  "int"},
    {"name": "CAUSE", "type":   "int"},
    {"name": "DATALEN", "type": "int"},
    {"name": "HOMEMCC", "type": "string"},
    {"name": "HOMEMNC", "type": "string"},
    {"name": "HOMEPROID", "type":   "bigint"},
    {"name": "HOMEAREAID", "type":  "bigint"},
    {"name": "SPNO", "type":    "string"},
    {"name": "CALLERCC", "type":    "string"},
    {"name": "CALLERAREAID", "type":    "bigint"},
    {"name": "CALLERNUMTYPE", "type":   "int"},
    {"name": "CALLEROPRID", "type": "bigint"},
    {"name": "ENCRYPT_VERSION", "type": "int"},
    {"name": "RESERVED1", "type":   "string"},
    {"name": "RESERVED2", "type":   "string"},
    {"name": "RESERVED3", "type":   "string"},
    {"name": "RESERVED4", "type":   "string"},
    {"name": "RESERVED5", "type":   "bigint"},
    {"name": "RESERVED6", "type":   "bigint"},
    {"name": "RESERVED7", "type":   "bigint"},
    {"name": "RESERVED8", "type":   "bigint"},
    {"name": "FILELOCATION", "type":    "string"},
    {"name": "OFFSET_DSI", "type":  "string"},
    {"name": "PROBEID", "type": "bigint"},
    {"name": "PROBEID2", "type":    "bigint"},
    {"name": "GROUPID", "type": "int"},
    {"name": "LNKOPC", "type":  "int"},
    {"name": "LNKDPC", "type":  "int"},
    {"name": "LNKSRCIP", "type":    "bigint"},
    {"name": "LNKSRCPORT", "type":  "int"},
    {"name": "LNKDESTIP", "type":   "bigint"},
    {"name": "LNKDESTPORT", "type": "int"},
    {"name": "OPPTYPE", "type": "int"},
    {"name": "VASSERVICETYPE", "type":  "int"},
    {"name": "SEGREF", "type":  "int"},
    {"name": "SEGTOTALNUM", "type": "int"},
    {"name": "SEGSEQ", "type":  "int"},
    {"name": "AFIRSTXDRID", "type": "string"},
    {"name": "FIRFAILTIME", "type": "bigint"},
    {"name": "LAYER1ID", "type":    "int"},
    {"name": "LAYER2ID", "type":    "int"},
    {"name": "LAYER3ID", "type":    "int"},
    {"name": "LAYER4ID", "type":    "int"},
    {"name": "LAYER5ID", "type":    "int"},
    {"name": "LAYER6ID", "type":    "int"},
    {"name": "LAST_ACCESS_TYPE", "type":    "int"},
    {"name": "E2EFIRFAILPROT", "type":  "bigint"},
    {"name": "E2EFIRFAILPD", "type":    "int"},
    {"name": "E2EFIRFAILMSG", "type":   "int"},
    {"name": "E2EFIRFAILCAUSE", "type": "bigint"},
    {"name": "FIRST_LAC", "type":   "string"},
    {"name": "FIRST_CI", "type":    "string"},
    {"name": "FIRST_RAT", "type":   "int"},
    {"name": "LAST_LAC", "type":    "string"},
    {"name": "LAST_CI", "type": "string"},
    {"name": "LONGITUDE", "type":   "bigint"},
    {"name": "LATITUDE", "type":    "bigint"},
    {"name": "HEIGHT", "type":  "int"},
    {"name": "RASTERLONGITUDE", "type": "bigint"},
    {"name": "RASTERLATITUDE", "type":  "bigint"},
    {"name": "RASTERALTITUDE", "type":  "int"},
    {"name": "FREQUENCYSPOT", "type":   "int"},
    {"name": "CLUTTER", "type": "int"},
    {"name": "USERBEHAVIOR", "type":    "int"},
    {"name": "SPEED", "type":   "int"},
    {"name": "CREDIBILITY", "type": "int"},
    {"name": "OLD_TMSI", "type":    "string"},
    {"name": "AUTH_SEC_REQ_TIME", "type":   "bigint"},
    {"name": "CLASSMARK_REQ_TIME", "type":  "bigint"},
    {"name": "CLASSMARK_UPDATE_TIME", "type":   "bigint"},
    {"name": "PREPAID_FLAG", "type":    "int"},
    {"name": "SMSC_TIMESTAMP", "type":  "string"},
    {"name": "FIRSTMNC", "type":    "string"},
    {"name": "SRV_ATTR_ID", "type": "string"},
    {"name": "MSC_GT", "type":  "string"},
    {"name": "na", "type": "string"}
  ]
}